curlr/__init__.py
curlr/main.py
tests/__init__.py
tests/example.py
curlr-0.1.2.dist-info/LICENSE
curlr-0.1.2.dist-info/METADATA
curlr-0.1.2.dist-info/WHEEL
curlr-0.1.2.dist-info/top_level.txt
curlr-0.1.2.dist-info/RECORD
