Metadata-Version: 2.1
Name: curlr
Version: 0.1.2
Summary: A Python package to parse and execute cURL commands
Home-page: https://github.com/schizoprada/curlr
Author: Joel Yisrael
Author-email: joel@highlyawear.com
Classifier: Development Status :: 3 - Alpha
Classifier: Intended Audience :: Developers
Classifier: License :: OSI Approved :: MIT License
Classifier: Operating System :: OS Independent
Classifier: Programming Language :: Python :: 3
Classifier: Programming Language :: Python :: 3.6
Classifier: Programming Language :: Python :: 3.7
Classifier: Programming Language :: Python :: 3.8
Classifier: Programming Language :: Python :: 3.9
Requires-Python: >=3.6
License-File: LICENSE
Requires-Dist: requests >=2.25.1
